slicemap/__init__.py
slicemap/benchmarks.py
slicemap/plotting.py
slicemap/slicemap.py
slicemap-1.2.0.dist-info/METADATA
slicemap-1.2.0.dist-info/WHEEL
slicemap-1.2.0.dist-info/licenses/LICENSE.txt
slicemap-1.2.0.dist-info/RECORD
