Metadata-Version: 2.4
Name: slicemap
Version: 1.2.0
Summary: Tiny dict-like structure with key slicing.
Project-URL: Home, https://github.com/gahaalt/slicemap
Project-URL: Documentation, https://github.com/sjmikler/slicemap/blob/main/docs
Author-email: Szymon Mikler <sjmikler@gmail.com>
License: MIT
License-File: LICENSE.txt
Classifier: License :: OSI Approved :: MIT License
Classifier: Programming Language :: Python :: 3
Classifier: Programming Language :: Python :: 3.7
Classifier: Programming Language :: Python :: 3.8
Classifier: Programming Language :: Python :: 3.9
Classifier: Programming Language :: Python :: 3.10
Classifier: Programming Language :: Python :: 3.11
Classifier: Programming Language :: Python :: 3.12
Classifier: Programming Language :: Python :: 3.13
Requires-Python: >=3.7
Requires-Dist: sortedcontainers
Provides-Extra: dev
Requires-Dist: hatch; extra == 'dev'
Requires-Dist: pyright; extra == 'dev'
Requires-Dist: pytest; extra == 'dev'
Requires-Dist: pytest-cov; extra == 'dev'
Requires-Dist: ruff; extra == 'dev'
Requires-Dist: twine; extra == 'dev'
